{"id":"index.html","dependencies":[{"name":"/home/fill/Documents/entrepot/package.json","includedInParent":true,"mtime":1533747202799},{"name":"./index.scss","dynamic":true,"parent":"/home/fill/Documents/entrepot/src/demo/index.html","resolved":"/home/fill/Documents/entrepot/src/demo/index.scss"},{"name":"./index.ts","dynamic":true,"parent":"/home/fill/Documents/entrepot/src/demo/index.html","resolved":"/home/fill/Documents/entrepot/src/demo/index.ts"}],"generated":{"html":"<html>\n<head>\n    <meta charset=\"UTF-8\">\n    <meta name=\"viewport\" content=\"width=device-width, user-scalable=no, initial-scale=1.0, maximum-scale=1.0, minimum-scale=1.0\">\n    <meta http-equiv=\"X-UA-Compatible\" content=\"ie=edge\">\n    <link rel=\"stylesheet\" href=\"https://cdnjs.cloudflare.com/ajax/libs/skeleton/2.0.4/skeleton.min.css\">\n    <link rel=\"stylesheet\" href=\"/e5f2ed3275e1a8c381a942e1faf47fa6.css\">\n    <title>Document</title>\n</head>\n<body>\n    <div class=\"container\" id=\"app-root\">\n        <h1>Store test</h1>\n        <hr>\n        <section>\n            <h3>Set values</h3>\n            <div class=\"row\">\n                <div class=\"six columns\">\n                    <div>\n                        <label for=\"set-namespace\">Set namespace</label>\n                        <input class=\"u-full-width\" type=\"text\" id=\"set-namespace\" required=\"\">\n                    </div>\n                    <div>\n                        <label for=\"set-key\">Set key</label>\n                        <input class=\"u-full-width\" type=\"text\" id=\"set-key\">\n                    </div>\n                    <div>\n                        <label for=\"set-value\">Set value</label>\n                        <textarea class=\"u-full-width\" placeholder=\"Provide value\" id=\"set-value\" required=\"\"></textarea>\n                    </div>\n                    <button class=\"button-primary\" id=\"set-value-button\">Set values</button>\n                </div>\n                <div class=\"six columns\">\n                    <label for=\"store-snapshot\">Store snapshot</label>\n                    <pre><code id=\"store-snapshot\">no value</code></pre>\n                </div>\n            </div>\n        </section>\n        <hr>\n        <section>\n            <h2>Retrieve values &amp; history</h2>\n            <div class=\"row\">\n                <div class=\"six columns\">\n                    <div>\n                        <label for=\"get-namespace\">Get namespace</label>\n                        <input class=\"u-full-width\" type=\"text\" id=\"get-namespace\">\n                    </div>\n                    <div>\n                        <label for=\"get-key\">Get key</label>\n                        <input class=\"u-full-width\" type=\"text\" id=\"get-key\" required=\"\">\n                    </div>\n                    <button class=\"button-primary\" id=\"get-value-button\">Get values</button>\n                </div>\n                <div class=\"six columns\">\n                    <label for=\"get-value\">Current value</label>\n                    <pre><code id=\"get-value\">no value</code></pre>\n                    <label for=\"get-history\">Previous values</label>\n                    <div id=\"get-history\"></div>\n                </div>\n            </div>\n        </section>\n    </div>\n    <script src=\"/552a23dab9aa91077b4b303e8a030cc4.js\"></script>\n</body>\n</html>\n"},"hash":"263349e30dc127e06469684fe055e295","cacheData":{}}